bosch_thermostat_http/__init__.py
bosch_thermostat_http/bosch_examples.py
bosch_thermostat_http/bosch_rawscan_cli.py
bosch_thermostat_http/circuit.py
bosch_thermostat_http/circuits.py
bosch_thermostat_http/const.py
bosch_thermostat_http/db.py
bosch_thermostat_http/encryption.py
bosch_thermostat_http/errors.py
bosch_thermostat_http/exceptions.py
bosch_thermostat_http/gateway.py
bosch_thermostat_http/helper.py
bosch_thermostat_http/http_connector.py
bosch_thermostat_http/schedule.py
bosch_thermostat_http/sensors.py
bosch_thermostat_http/strings.py
bosch_thermostat_http/version.py
bosch_thermostat_http/db/can.json
bosch_thermostat_http/db/db.json
bosch_thermostat_http/db/default.json
bosch_thermostat_http/db/rc300.json
bosch_thermostat_http_client-0.7.2.dist-info/LICENSE.txt
bosch_thermostat_http_client-0.7.2.dist-info/METADATA
bosch_thermostat_http_client-0.7.2.dist-info/WHEEL
bosch_thermostat_http_client-0.7.2.dist-info/entry_points.txt
bosch_thermostat_http_client-0.7.2.dist-info/top_level.txt
bosch_thermostat_http_client-0.7.2.dist-info/RECORD
