Metadata-Version: 2.1
Name: bosch-thermostat-http-client
Version: 0.7.2
Summary: Python API for talking to Bosch™ Heating gateway using HTTP 
Home-page: https://github.com/moustic999/bosch-thermostat-http-client-python.git
Author: Ludovic Laurent
Author-email: ludovic.laurent@gmail.com
Maintainer: Ludovic Laurent
Maintainer-email: ludovic.laurent@gmail.com
License: Apache License 2.0
Download-URL: https://github.com/moustic999/bosch-thermostat-http-client-python/archive/0.7.2.zip
Platform: UNKNOWN
Classifier: Development Status :: 3 - Alpha
Classifier: Intended Audience :: Developers
Classifier: Intended Audience :: End Users/Desktop
Classifier: Environment :: Console
Classifier: Topic :: Other/Nonlisted Topic
Classifier: Topic :: Utilities
Classifier: Topic :: Software Development :: Libraries :: Python Modules
Classifier: Programming Language :: Python
Classifier: Programming Language :: Python :: 3.5
Classifier: Programming Language :: Python :: 3.6
Classifier: Programming Language :: Python :: 3.7
Requires-Dist: pyaes (>=1.6.1)
Requires-Dist: aiohttp
Requires-Dist: click (>=7)
